odoo/addons/sale_coupon_selection_wizard/README.rst
odoo/addons/sale_coupon_selection_wizard/__init__.py
odoo/addons/sale_coupon_selection_wizard/__manifest__.py
odoo/addons/sale_coupon_selection_wizard/controllers/__init__.py
odoo/addons/sale_coupon_selection_wizard/controllers/main.py
odoo/addons/sale_coupon_selection_wizard/i18n/es.po
odoo/addons/sale_coupon_selection_wizard/i18n/sale_coupon_selection_wizard.pot
odoo/addons/sale_coupon_selection_wizard/models/__init__.py
odoo/addons/sale_coupon_selection_wizard/models/sale_order.py
odoo/addons/sale_coupon_selection_wizard/readme/CONTRIBUTORS.rst
odoo/addons/sale_coupon_selection_wizard/readme/DESCRIPTION.rst
odoo/addons/sale_coupon_selection_wizard/readme/USAGE.rst
odoo/addons/sale_coupon_selection_wizard/security/ir.model.access.csv
odoo/addons/sale_coupon_selection_wizard/static/description/icon.png
odoo/addons/sale_coupon_selection_wizard/static/description/index.html
odoo/addons/sale_coupon_selection_wizard/static/src/js/coupon_selection_wizard_mixin.js
odoo/addons/sale_coupon_selection_wizard/static/src/js/coupon_selection_wizard_view.js
odoo/addons/sale_coupon_selection_wizard/static/src/scss/coupon_selection_wizard.scss
odoo/addons/sale_coupon_selection_wizard/tests/__init__.py
odoo/addons/sale_coupon_selection_wizard/tests/test_sale_coupon_selection_wizard.py
odoo/addons/sale_coupon_selection_wizard/views/sale_order_views.xml
odoo/addons/sale_coupon_selection_wizard/views/templates.xml
odoo/addons/sale_coupon_selection_wizard/wizards/__init__.py
odoo/addons/sale_coupon_selection_wizard/wizards/coupon_selection_wizard.py
odoo/addons/sale_coupon_selection_wizard/wizards/coupon_selection_wizard_views.xml
odoo_addon_sale_coupon_selection_wizard-15.0.1.0.0.5.dist-info/METADATA
odoo_addon_sale_coupon_selection_wizard-15.0.1.0.0.5.dist-info/WHEEL
odoo_addon_sale_coupon_selection_wizard-15.0.1.0.0.5.dist-info/top_level.txt
odoo_addon_sale_coupon_selection_wizard-15.0.1.0.0.5.dist-info/RECORD
